<score-partwise version="3.0">
  <work>
    <work-title>&#350;em'I R&#251;huna Cismimi&#133;</work-title>
  </work>
  <identification>
    <creator type="composer">Sultan Veled</creator>
    <creator type="poet">?</creator>
    <encoding>
      <encoder>Burak Uyar</encoder>
      <software>https://github.com/burakuyar/MusicXMLConverter</software>
    </encoding>
    <relation>http://musicbrainz.org/work/998e63be-a27f-4385-815d-cd3f1afd32ca</relation>
  </identification>
  <part-list>
    <score-part id="P1">
      <part-name>Music</part-name>
    </score-part>
  </part-list>
  <part id="P1">
    <measure number="1-0">
      <direction placement="above">
        <direction-type>
          <metronome>
            <beat-unit>quarter</beat-unit>
            <per-minute>54</per-minute>
          </metronome>
        </direction-type>
        <direction-type>
          <words default-y="35">Makam: Seg&#226;h-M&#226;ye, Form: &#304;l&#226;h&#238;, Usul: Devr-i Rev&#226;n </words>
        </direction-type>
        <sound tempo="54" />
      </direction>
      <attributes>
        <divisions>96</divisions>
        <key />
        <time>
          <beats>14</beats>
          <beat-type>8</beat-type>
        </time>
      </attributes>
      <note>
        
        <pitch>
          <step>D</step>
          <octave>5</octave>
        </pitch>
        <duration>96</duration>
        <type>quarter</type>
        <lyric name="VOCAL_SECTION">
          <syllabic>single</syllabic>
          <text>&#350;em </text>
        </lyric>
      </note>
      <note>
        
        <pitch>
          <step>E</step>
          <octave>5</octave>
        </pitch>
        <duration>48</duration>
        <type>eighth</type>
        <lyric>
          <text />
        </lyric>
      </note>
      <note>
        
        <pitch>
          <step>D</step>
          <octave>5</octave>
        </pitch>
        <duration>48</duration>
        <type>eighth</type>
        <lyric>
          <syllabic>single</syllabic>
          <text>i </text>
        </lyric>
      </note>
      <note>
        
        <pitch>
          <step>C</step>
          <octave>5</octave>
        </pitch>
        <duration>24</duration>
        <type>16th</type>
        <lyric>
          <text />
        </lyric>
      </note>
      <note>
        
        <pitch>
          <step>D</step>
          <octave>5</octave>
        </pitch>
        <duration>24</duration>
        <type>16th</type>
        <lyric>
          <text />
        </lyric>
      </note>
      <note>
        
        <pitch>
          <step>C</step>
          <octave>5</octave>
        </pitch>
        <duration>48</duration>
        <type>eighth</type>
        <lyric>
          <text />
        </lyric>
      </note>
      <note>
        
        <pitch>
          <step>B</step>
          <alter>-0.5</alter>
          <octave>4</octave>
        </pitch>
        <duration>48</duration>
        <type>eighth</type>
        <accidental>quarter-flat</accidental>
        <lyric>
          <text />
        </lyric>
      </note>
      <note>
        
        <pitch>
          <step>A</step>
          <octave>4</octave>
        </pitch>
        <duration>48</duration>
        <type>eighth</type>
        <lyric>
          <syllabic>begin</syllabic>
          <text>r&#251;</text>
        </lyric>
      </note>
      <note>
        
        <grace steal-time-following="10" />
        <pitch>
          <step>B</step>
          <octave>4</octave>
        </pitch>
        <lyric>
          <text />
        </lyric>
      </note>
      <note>
        
        <pitch>
          <step>A</step>
          <octave>4</octave>
        </pitch>
        <duration>48</duration>
        <type>eighth</type>
        <lyric>
          <text />
        </lyric>
      </note>
      <note>
        
        <pitch>
          <step>B</step>
          <alter>-0.5</alter>
          <octave>4</octave>
        </pitch>
        <duration>48</duration>
        <type>eighth</type>
        <accidental>quarter-flat</accidental>
        <lyric>
          <syllabic>end</syllabic>
          <text>hu</text>
        </lyric>
      </note>
      <note>
        
        <pitch>
          <step>C</step>
          <octave>5</octave>
        </pitch>
        <duration>48</duration>
        <type>eighth</type>
        <lyric>
          <syllabic>single</syllabic>
          <text>na </text>
        </lyric>
      </note>
      <note>
        
        <pitch>
          <step>B</step>
          <alter>-0.5</alter>
          <octave>4</octave>
        </pitch>
        <duration>24</duration>
        <type>16th</type>
        <accidental>quarter-flat</accidental>
        <lyric>
          <text />
        </lyric>
      </note>
      <note>
        
        <pitch>
          <step>C</step>
          <octave>5</octave>
        </pitch>
        <duration>24</duration>
        <type>16th</type>
        <lyric>
          <text />
        </lyric>
      </note>
      <note>
        
        <pitch>
          <step>D</step>
          <octave>5</octave>
        </pitch>
        <duration>96</duration>
        <type>quarter</type>
        <lyric>
          <syllabic>begin</syllabic>
          <text>cis</text>
        </lyric>
      </note>
    </measure>
    <measure number="2-0">
      <attributes />
      <note>
        
        <pitch>
          <step>A</step>
          <octave>4</octave>
        </pitch>
        <duration>96</duration>
        <type>quarter</type>
        <lyric>
          <syllabic>end</syllabic>
          <text>mi</text>
        </lyric>
      </note>
      <note>
        
        <pitch>
          <step>B</step>
          <alter>-0.5</alter>
          <octave>4</octave>
        </pitch>
        <duration>48</duration>
        <type>eighth</type>
        <accidental>quarter-flat</accidental>
        <lyric>
          <syllabic>single</syllabic>
          <text>mi </text>
        </lyric>
      </note>
      <note>
        
        <pitch>
          <step>C</step>
          <octave>5</octave>
        </pitch>
        <duration>72</duration>
        <type>eighth</type>
        <dot />
        <lyric>
          <syllabic>begin</syllabic>
          <text>per</text>
        </lyric>
      </note>
      <note>
        
        <pitch>
          <step>B</step>
          <alter>-0.5</alter>
          <octave>4</octave>
        </pitch>
        <duration>24</duration>
        <type>16th</type>
        <accidental>quarter-flat</accidental>
        <lyric>
          <text />
        </lyric>
      </note>
      <note>
        
        <pitch>
          <step>D</step>
          <octave>5</octave>
        </pitch>
        <duration>48</duration>
        <type>eighth</type>
        <lyric>
          <text />
        </lyric>
      </note>
      <note>
        
        <pitch>
          <step>C</step>
          <octave>5</octave>
        </pitch>
        <duration>24</duration>
        <type>16th</type>
        <lyric>
          <text />
        </lyric>
      </note>
      <note>
        
        <pitch>
          <step>B</step>
          <alter>-0.5</alter>
          <octave>4</octave>
        </pitch>
        <duration>24</duration>
        <type>16th</type>
        <accidental>quarter-flat</accidental>
        <lyric>
          <text />
        </lyric>
      </note>
      <note>
        
        <grace steal-time-previous="10" />
        <pitch>
          <step>C</step>
          <octave>5</octave>
        </pitch>
        <lyric>
          <text />
        </lyric>
      </note>
      <note>
        
        <pitch>
          <step>B</step>
          <alter>-0.5</alter>
          <octave>4</octave>
        </pitch>
        <duration>48</duration>
        <type>eighth</type>
        <accidental>quarter-flat</accidental>
        <lyric>
          <syllabic>end</syllabic>
          <text>v&#226; </text>
        </lyric>
      </note>
      <note>
        
        <pitch>
          <step>C</step>
          <octave>5</octave>
        </pitch>
        <duration>48</duration>
        <type>eighth</type>
        <lyric>
          <text />
        </lyric>
      </note>
      <note>
        
        <pitch>
          <step>B</step>
          <alter>-0.5</alter>
          <octave>4</octave>
        </pitch>
        <duration>24</duration>
        <type>16th</type>
        <accidental>quarter-flat</accidental>
        <lyric>
          <text />
        </lyric>
      </note>
      <note>
        
        <pitch>
          <step>A</step>
          <octave>4</octave>
        </pitch>
        <duration>24</duration>
        <type>16th</type>
        <lyric>
          <text />
        </lyric>
      </note>
      <note>
        
        <pitch>
          <step>A</step>
          <octave>4</octave>
        </pitch>
        <duration>144</duration>
        <type>quarter</type>
        <dot />
        <lyric>
          <text />
        </lyric>
      </note>
      <note>
        
        <rest />
        <duration>48</duration>
        <type>eighth</type>
        <lyric>
          <text />
        </lyric>
      </note>
    </measure>
    <measure number="3-0">
      <attributes />
      <note>
        
        <pitch>
          <step>G</step>
          <octave>5</octave>
        </pitch>
        <duration>96</duration>
        <type>quarter</type>
        <lyric>
          <syllabic>begin</syllabic>
          <text>v&#226;</text>
        </lyric>
      </note>
      <note>
        
        <pitch>
          <step>F</step>
          <alter>+1</alter>
          <octave>5</octave>
        </pitch>
        <duration>48</duration>
        <type>eighth</type>
        <accidental>sharp</accidental>
        <lyric>
          <text />
        </lyric>
      </note>
      <note>
        
        <pitch>
          <step>G</step>
          <octave>5</octave>
        </pitch>
        <duration>48</duration>
        <type>eighth</type>
        <lyric>
          <text />
        </lyric>
      </note>
      <note>
        
        <pitch>
          <step>F</step>
          <alter>+1</alter>
          <octave>5</octave>
        </pitch>
        <duration>48</duration>
        <type>eighth</type>
        <accidental>sharp</accidental>
        <lyric>
          <text />
        </lyric>
      </note>
      <note>
        
        <pitch>
          <step>E</step>
          <alter>-0.5</alter>
          <octave>5</octave>
        </pitch>
        <duration>48</duration>
        <type>eighth</type>
        <accidental>quarter-flat</accidental>
        <lyric>
          <text />
        </lyric>
      </note>
      <note>
        
        <pitch>
          <step>D</step>
          <octave>5</octave>
        </pitch>
        <duration>48</duration>
        <type>eighth</type>
        <lyric>
          <text />
        </lyric>
      </note>
      <note>
        
        <pitch>
          <step>D</step>
          <octave>5</octave>
        </pitch>
        <duration>96</duration>
        <type>quarter</type>
        <lyric>
          <text />
        </lyric>
      </note>
      <note>
        
        <pitch>
          <step>E</step>
          <alter>-0.5</alter>
          <octave>5</octave>
        </pitch>
        <duration>48</duration>
        <type>eighth</type>
        <accidental>quarter-flat</accidental>
        <lyric>
          <text />
        </lyric>
      </note>
      <note>
        
        <pitch>
          <step>F</step>
          <alter>+1</alter>
          <octave>5</octave>
        </pitch>
        <duration>48</duration>
        <type>eighth</type>
        <accidental>sharp</accidental>
        <lyric>
          <text />
        </lyric>
      </note>
      <note>
        
        <pitch>
          <step>G</step>
          <octave>5</octave>
        </pitch>
        <duration>48</duration>
        <type>eighth</type>
        <lyric>
          <text />
        </lyric>
      </note>
      <note>
        
        <pitch>
          <step>F</step>
          <alter>+1</alter>
          <octave>5</octave>
        </pitch>
        <duration>48</duration>
        <type>eighth</type>
        <accidental>sharp</accidental>
        <lyric>
          <text />
        </lyric>
      </note>
      <note>
        
        <pitch>
          <step>E</step>
          <alter>-0.5</alter>
          <octave>5</octave>
        </pitch>
        <duration>48</duration>
        <type>eighth</type>
        <accidental>quarter-flat</accidental>
        <lyric>
          <text />
        </lyric>
      </note>
    </measure>
    <measure number="4-0">
      <attributes />
      <note>
        
        <pitch>
          <step>D</step>
          <octave>5</octave>
        </pitch>
        <duration>96</duration>
        <type>quarter</type>
        <lyric>
          <syllabic>end</syllabic>
          <text>ne </text>
        </lyric>
      </note>
      <note>
        
        <pitch>
          <step>C</step>
          <octave>5</octave>
        </pitch>
        <duration>24</duration>
        <type>16th</type>
        <lyric>
          <syllabic>begin</syllabic>
          <text>d&#252;</text>
        </lyric>
      </note>
      <note>
        
        <pitch>
          <step>B</step>
          <alter>-0.5</alter>
          <octave>4</octave>
        </pitch>
        <duration>24</duration>
        <type>16th</type>
        <accidental>quarter-flat</accidental>
        <lyric>
          <text />
        </lyric>
      </note>
      <note>
        
        <pitch>
          <step>C</step>
          <octave>5</octave>
        </pitch>
        <duration>72</duration>
        <type>eighth</type>
        <dot />
        <lyric>
          <syllabic>end</syllabic>
          <text>&#351;&#252;r</text>
        </lyric>
      </note>
      <note>
        
        <pitch>
          <step>B</step>
          <alter>-0.5</alter>
          <octave>4</octave>
        </pitch>
        <duration>24</duration>
        <type>16th</type>
        <accidental>quarter-flat</accidental>
        <lyric>
          <text />
        </lyric>
      </note>
      <note>
        
        <pitch>
          <step>D</step>
          <octave>5</octave>
        </pitch>
        <duration>48</duration>
        <type>eighth</type>
        <lyric>
          <text />
        </lyric>
      </note>
      <note>
        
        <pitch>
          <step>C</step>
          <octave>5</octave>
        </pitch>
        <duration>24</duration>
        <type>16th</type>
        <lyric>
          <text />
        </lyric>
      </note>
      <note>
        
        <pitch>
          <step>B</step>
          <alter>-0.5</alter>
          <octave>4</octave>
        </pitch>
        <duration>24</duration>
        <type>16th</type>
        <accidental>quarter-flat</accidental>
        <lyric>
          <text />
        </lyric>
      </note>
      <note>
        
        <grace steal-time-previous="10" />
        <pitch>
          <step>C</step>
          <octave>5</octave>
        </pitch>
        <lyric>
          <text />
        </lyric>
      </note>
      <note>
        
        <pitch>
          <step>B</step>
          <alter>-0.5</alter>
          <octave>4</octave>
        </pitch>
        <duration>144</duration>
        <type>quarter</type>
        <dot />
        <accidental>quarter-flat</accidental>
        <lyric>
          <syllabic>single</syllabic>
          <text>d&#252;m  </text>
          <end-line />
        </lyric>
      </note>
      <note>
        
        <pitch>
          <step>B</step>
          <alter>-0.5</alter>
          <octave>4</octave>
        </pitch>
        <duration>48</duration>
        <type>eighth</type>
        <accidental>quarter-flat</accidental>
        <lyric>
          <text />
        </lyric>
      </note>
      <note>
        
        <pitch>
          <step>C</step>
          <octave>5</octave>
        </pitch>
        <duration>48</duration>
        <type>eighth</type>
        <lyric>
          <text />
        </lyric>
      </note>
      <note>
        
        <pitch>
          <step>D</step>
          <octave>5</octave>
        </pitch>
        <duration>96</duration>
        <type>quarter</type>
        <lyric>
          <text />
        </lyric>
      </note>
    </measure>
    <measure number="5-0">
      <attributes />
      <note>
        
        <pitch>
          <step>D</step>
          <octave>5</octave>
        </pitch>
        <duration>96</duration>
        <type>quarter</type>
        <lyric name="VOCAL_SECTION">
          <syllabic>begin</syllabic>
          <text>Ev</text>
        </lyric>
      </note>
      <note>
        
        <pitch>
          <step>E</step>
          <octave>5</octave>
        </pitch>
        <duration>48</duration>
        <type>eighth</type>
        <lyric>
          <text />
        </lyric>
      </note>
      <note>
        
        <pitch>
          <step>D</step>
          <octave>5</octave>
        </pitch>
        <duration>48</duration>
        <type>eighth</type>
        <lyric>
          <syllabic>end</syllabic>
          <text>r&#226;k_</text>
        </lyric>
      </note>
      <note>
        
        <pitch>
          <step>C</step>
          <octave>5</octave>
        </pitch>
        <duration>24</duration>
        <type>16th</type>
        <lyric>
          <text />
        </lyric>
      </note>
      <note>
        
        <pitch>
          <step>D</step>
          <octave>5</octave>
        </pitch>
        <duration>24</duration>
        <type>16th</type>
        <lyric>
          <text />
        </lyric>
      </note>
      <note>
        
        <pitch>
          <step>C</step>
          <octave>5</octave>
        </pitch>
        <duration>48</duration>
        <type>eighth</type>
        <lyric>
          <text />
        </lyric>
      </note>
      <note>
        
        <pitch>
          <step>B</step>
          <alter>-0.5</alter>
          <octave>4</octave>
        </pitch>
        <duration>48</duration>
        <type>eighth</type>
        <accidental>quarter-flat</accidental>
        <lyric>
          <text />
        </lyric>
      </note>
      <note>
        
        <pitch>
          <step>A</step>
          <octave>4</octave>
        </pitch>
        <duration>48</duration>
        <type>eighth</type>
        <lyric>
          <syllabic>single</syllabic>
          <text>&#305; </text>
        </lyric>
      </note>
      <note>
        
        <grace steal-time-previous="10" />
        <pitch>
          <step>B</step>
          <octave>4</octave>
        </pitch>
        <lyric>
          <text />
        </lyric>
      </note>
      <note>
        
        <pitch>
          <step>A</step>
          <octave>4</octave>
        </pitch>
        <duration>48</duration>
        <type>eighth</type>
        <lyric>
          <text />
        </lyric>
      </note>
      <note>
        
        <pitch>
          <step>B</step>
          <alter>-0.5</alter>
          <octave>4</octave>
        </pitch>
        <duration>48</duration>
        <type>eighth</type>
        <accidental>quarter-flat</accidental>
        <lyric>
          <syllabic>begin</syllabic>
          <text>di</text>
        </lyric>
      </note>
      <note>
        
        <pitch>
          <step>C</step>
          <octave>5</octave>
        </pitch>
        <duration>48</duration>
        <type>eighth</type>
        <lyric>
          <syllabic>end</syllabic>
          <text>li </text>
        </lyric>
      </note>
      <note>
        
        <pitch>
          <step>B</step>
          <alter>-0.5</alter>
          <octave>4</octave>
        </pitch>
        <duration>24</duration>
        <type>16th</type>
        <accidental>quarter-flat</accidental>
        <lyric>
          <text />
        </lyric>
      </note>
      <note>
        
        <pitch>
          <step>C</step>
          <octave>5</octave>
        </pitch>
        <duration>24</duration>
        <type>16th</type>
        <lyric>
          <text />
        </lyric>
      </note>
      <note>
        
        <pitch>
          <step>D</step>
          <octave>5</octave>
        </pitch>
        <duration>96</duration>
        <type>quarter</type>
        <lyric>
          <syllabic>begin</syllabic>
          <text>&#226;</text>
        </lyric>
      </note>
    </measure>
    <measure number="6-0">
      <attributes />
      <note>
        
        <pitch>
          <step>A</step>
          <octave>4</octave>
        </pitch>
        <duration>96</duration>
        <type>quarter</type>
        <lyric>
          <syllabic>end</syllabic>
          <text>te&#351;_</text>
        </lyric>
      </note>
      <note>
        
        <pitch>
          <step>B</step>
          <alter>-0.5</alter>
          <octave>4</octave>
        </pitch>
        <duration>48</duration>
        <type>eighth</type>
        <accidental>quarter-flat</accidental>
        <lyric>
          <syllabic>single</syllabic>
          <text>i </text>
        </lyric>
      </note>
      <note>
        
        <pitch>
          <step>C</step>
          <octave>5</octave>
        </pitch>
        <duration>72</duration>
        <type>eighth</type>
        <dot />
        <lyric>
          <syllabic>begin</syllabic>
          <text>s&#251;</text>
        </lyric>
      </note>
      <note>
        
        <pitch>
          <step>B</step>
          <alter>-0.5</alter>
          <octave>4</octave>
        </pitch>
        <duration>24</duration>
        <type>16th</type>
        <accidental>quarter-flat</accidental>
        <lyric>
          <text />
        </lyric>
      </note>
      <note>
        
        <pitch>
          <step>D</step>
          <octave>5</octave>
        </pitch>
        <duration>48</duration>
        <type>eighth</type>
        <lyric>
          <text />
        </lyric>
      </note>
      <note>
        
        <pitch>
          <step>C</step>
          <octave>5</octave>
        </pitch>
        <duration>24</duration>
        <type>16th</type>
        <lyric>
          <text />
        </lyric>
      </note>
      <note>
        
        <pitch>
          <step>B</step>
          <alter>-0.5</alter>
          <octave>4</octave>
        </pitch>
        <duration>24</duration>
        <type>16th</type>
        <accidental>quarter-flat</accidental>
        <lyric>
          <text />
        </lyric>
      </note>
      <note>
        
        <grace steal-time-previous="10" />
        <pitch>
          <step>C</step>
          <octave>5</octave>
        </pitch>
        <lyric>
          <text />
        </lyric>
      </note>
      <note>
        
        <pitch>
          <step>B</step>
          <alter>-0.5</alter>
          <octave>4</octave>
        </pitch>
        <duration>48</duration>
        <type>eighth</type>
        <accidental>quarter-flat</accidental>
        <lyric>
          <syllabic>end</syllabic>
          <text>z&#226; </text>
        </lyric>
      </note>
      <note>
        
        <pitch>
          <step>C</step>
          <octave>5</octave>
        </pitch>
        <duration>48</duration>
        <type>eighth</type>
        <lyric>
          <text />
        </lyric>
      </note>
      <note>
        
        <pitch>
          <step>B</step>
          <alter>-0.5</alter>
          <octave>4</octave>
        </pitch>
        <duration>24</duration>
        <type>16th</type>
        <accidental>quarter-flat</accidental>
        <lyric>
          <text />
        </lyric>
      </note>
      <note>
        
        <pitch>
          <step>A</step>
          <octave>4</octave>
        </pitch>
        <duration>24</duration>
        <type>16th</type>
        <lyric>
          <text />
        </lyric>
      </note>
      <note>
        
        <pitch>
          <step>A</step>
          <octave>4</octave>
        </pitch>
        <duration>144</duration>
        <type>quarter</type>
        <dot />
        <lyric>
          <text />
        </lyric>
      </note>
      <note>
        
        <rest />
        <duration>48</duration>
        <type>eighth</type>
        <lyric>
          <text />
        </lyric>
      </note>
    </measure>
    <measure number="7-0">
      <attributes />
      <note>
        
        <pitch>
          <step>G</step>
          <octave>5</octave>
        </pitch>
        <duration>96</duration>
        <type>quarter</type>
        <lyric>
          <syllabic>begin</syllabic>
          <text>z&#226;</text>
        </lyric>
      </note>
      <note>
        
        <pitch>
          <step>F</step>
          <alter>+1</alter>
          <octave>5</octave>
        </pitch>
        <duration>48</duration>
        <type>eighth</type>
        <accidental>sharp</accidental>
        <lyric>
          <text />
        </lyric>
      </note>
      <note>
        
        <pitch>
          <step>G</step>
          <octave>5</octave>
        </pitch>
        <duration>48</duration>
        <type>eighth</type>
        <lyric>
          <text />
        </lyric>
      </note>
      <note>
        
        <pitch>
          <step>F</step>
          <alter>+1</alter>
          <octave>5</octave>
        </pitch>
        <duration>48</duration>
        <type>eighth</type>
        <accidental>sharp</accidental>
        <lyric>
          <text />
        </lyric>
      </note>
      <note>
        
        <pitch>
          <step>E</step>
          <alter>-0.5</alter>
          <octave>5</octave>
        </pitch>
        <duration>48</duration>
        <type>eighth</type>
        <accidental>quarter-flat</accidental>
        <lyric>
          <text />
        </lyric>
      </note>
      <note>
        
        <pitch>
          <step>D</step>
          <octave>5</octave>
        </pitch>
        <duration>48</duration>
        <type>eighth</type>
        <lyric>
          <text />
        </lyric>
      </note>
      <note>
        
        <pitch>
          <step>D</step>
          <octave>5</octave>
        </pitch>
        <duration>96</duration>
        <type>quarter</type>
        <lyric>
          <text />
        </lyric>
      </note>
      <note>
        
        <pitch>
          <step>E</step>
          <alter>-0.5</alter>
          <octave>5</octave>
        </pitch>
        <duration>48</duration>
        <type>eighth</type>
        <accidental>quarter-flat</accidental>
        <lyric>
          <text />
        </lyric>
      </note>
      <note>
        
        <pitch>
          <step>F</step>
          <alter>+1</alter>
          <octave>5</octave>
        </pitch>
        <duration>48</duration>
        <type>eighth</type>
        <accidental>sharp</accidental>
        <lyric>
          <text />
        </lyric>
      </note>
      <note>
        
        <pitch>
          <step>G</step>
          <octave>5</octave>
        </pitch>
        <duration>48</duration>
        <type>eighth</type>
        <lyric>
          <text />
        </lyric>
      </note>
      <note>
        
        <pitch>
          <step>F</step>
          <alter>+1</alter>
          <octave>5</octave>
        </pitch>
        <duration>48</duration>
        <type>eighth</type>
        <accidental>sharp</accidental>
        <lyric>
          <text />
        </lyric>
      </note>
      <note>
        
        <pitch>
          <step>E</step>
          <alter>-0.5</alter>
          <octave>5</octave>
        </pitch>
        <duration>48</duration>
        <type>eighth</type>
        <accidental>quarter-flat</accidental>
        <lyric>
          <text />
        </lyric>
      </note>
    </measure>
    <measure number="8-0">
      <attributes />
      <note>
        
        <pitch>
          <step>D</step>
          <octave>5</octave>
        </pitch>
        <duration>96</duration>
        <type>quarter</type>
        <lyric>
          <syllabic>end</syllabic>
          <text>ne </text>
        </lyric>
      </note>
      <note>
        
        <pitch>
          <step>C</step>
          <octave>5</octave>
        </pitch>
        <duration>24</duration>
        <type>16th</type>
        <lyric>
          <syllabic>begin</syllabic>
          <text>d&#252;</text>
        </lyric>
      </note>
      <note>
        
        <pitch>
          <step>B</step>
          <alter>-0.5</alter>
          <octave>4</octave>
        </pitch>
        <duration>24</duration>
        <type>16th</type>
        <accidental>quarter-flat</accidental>
        <lyric>
          <text />
        </lyric>
      </note>
      <note>
        
        <pitch>
          <step>C</step>
          <octave>5</octave>
        </pitch>
        <duration>72</duration>
        <type>eighth</type>
        <dot />
        <lyric>
          <syllabic>end</syllabic>
          <text>&#351;&#252;r</text>
        </lyric>
      </note>
      <note>
        
        <pitch>
          <step>B</step>
          <alter>-0.5</alter>
          <octave>4</octave>
        </pitch>
        <duration>24</duration>
        <type>16th</type>
        <accidental>quarter-flat</accidental>
        <lyric>
          <text />
        </lyric>
      </note>
      <note>
        
        <pitch>
          <step>D</step>
          <octave>5</octave>
        </pitch>
        <duration>48</duration>
        <type>eighth</type>
        <lyric>
          <text />
        </lyric>
      </note>
      <note>
        
        <pitch>
          <step>C</step>
          <octave>5</octave>
        </pitch>
        <duration>24</duration>
        <type>16th</type>
        <lyric>
          <text />
        </lyric>
      </note>
      <note>
        
        <pitch>
          <step>B</step>
          <alter>-0.5</alter>
          <octave>4</octave>
        </pitch>
        <duration>24</duration>
        <type>16th</type>
        <accidental>quarter-flat</accidental>
        <lyric>
          <text />
        </lyric>
      </note>
      <note>
        
        <grace steal-time-previous="10" />
        <pitch>
          <step>C</step>
          <octave>5</octave>
        </pitch>
        <lyric>
          <text />
        </lyric>
      </note>
      <note>
        
        <pitch>
          <step>B</step>
          <alter>-0.5</alter>
          <octave>4</octave>
        </pitch>
        <duration>144</duration>
        <type>quarter</type>
        <dot />
        <accidental>quarter-flat</accidental>
        <lyric>
          <syllabic>single</syllabic>
          <text>d&#252;m  </text>
          <end-line />
        </lyric>
      </note>
      <note>
        
        <pitch>
          <step>B</step>
          <alter>-0.5</alter>
          <octave>4</octave>
        </pitch>
        <duration>48</duration>
        <type>eighth</type>
        <accidental>quarter-flat</accidental>
        <lyric>
          <text />
        </lyric>
      </note>
      <note>
        
        <pitch>
          <step>C</step>
          <octave>5</octave>
        </pitch>
        <duration>48</duration>
        <type>eighth</type>
        <lyric>
          <text />
        </lyric>
      </note>
      <note>
        
        <pitch>
          <step>D</step>
          <octave>5</octave>
        </pitch>
        <duration>96</duration>
        <type>quarter</type>
        <lyric>
          <text />
        </lyric>
      </note>
    </measure>
    <measure number="9-0">
      <attributes />
      <note>
        
        <pitch>
          <step>D</step>
          <octave>5</octave>
        </pitch>
        <duration>96</duration>
        <type>quarter</type>
        <lyric name="VOCAL_SECTION">
          <syllabic>single</syllabic>
          <text>&#350;em </text>
        </lyric>
      </note>
      <note>
        
        <pitch>
          <step>E</step>
          <octave>5</octave>
        </pitch>
        <duration>48</duration>
        <type>eighth</type>
        <lyric>
          <text />
        </lyric>
      </note>
      <note>
        
        <pitch>
          <step>D</step>
          <octave>5</octave>
        </pitch>
        <duration>48</duration>
        <type>eighth</type>
        <lyric>
          <syllabic>single</syllabic>
          <text>i </text>
        </lyric>
      </note>
      <note>
        
        <pitch>
          <step>C</step>
          <octave>5</octave>
        </pitch>
        <duration>24</duration>
        <type>16th</type>
        <lyric>
          <text />
        </lyric>
      </note>
      <note>
        
        <pitch>
          <step>D</step>
          <octave>5</octave>
        </pitch>
        <duration>24</duration>
        <type>16th</type>
        <lyric>
          <text />
        </lyric>
      </note>
      <note>
        
        <pitch>
          <step>C</step>
          <octave>5</octave>
        </pitch>
        <duration>48</duration>
        <type>eighth</type>
        <lyric>
          <text />
        </lyric>
      </note>
      <note>
        
        <pitch>
          <step>B</step>
          <alter>-0.5</alter>
          <octave>4</octave>
        </pitch>
        <duration>48</duration>
        <type>eighth</type>
        <accidental>quarter-flat</accidental>
        <lyric>
          <text />
        </lyric>
      </note>
      <note>
        
        <pitch>
          <step>A</step>
          <octave>4</octave>
        </pitch>
        <duration>48</duration>
        <type>eighth</type>
        <lyric>
          <syllabic>begin</syllabic>
          <text>r&#251;</text>
        </lyric>
      </note>
      <note>
        
        <grace steal-time-previous="10" />
        <pitch>
          <step>B</step>
          <octave>4</octave>
        </pitch>
        <lyric>
          <text />
        </lyric>
      </note>
      <note>
        
        <pitch>
          <step>A</step>
          <octave>4</octave>
        </pitch>
        <duration>48</duration>
        <type>eighth</type>
        <lyric>
          <text />
        </lyric>
      </note>
      <note>
        
        <pitch>
          <step>B</step>
          <alter>-0.5</alter>
          <octave>4</octave>
        </pitch>
        <duration>48</duration>
        <type>eighth</type>
        <accidental>quarter-flat</accidental>
        <lyric>
          <syllabic>end</syllabic>
          <text>hu</text>
        </lyric>
      </note>
      <note>
        
        <pitch>
          <step>C</step>
          <octave>5</octave>
        </pitch>
        <duration>48</duration>
        <type>eighth</type>
        <lyric>
          <syllabic>single</syllabic>
          <text>na </text>
        </lyric>
      </note>
      <note>
        
        <pitch>
          <step>B</step>
          <alter>-0.5</alter>
          <octave>4</octave>
        </pitch>
        <duration>24</duration>
        <type>16th</type>
        <accidental>quarter-flat</accidental>
        <lyric>
          <text />
        </lyric>
      </note>
      <note>
        
        <pitch>
          <step>C</step>
          <octave>5</octave>
        </pitch>
        <duration>24</duration>
        <type>16th</type>
        <lyric>
          <text />
        </lyric>
      </note>
      <note>
        
        <pitch>
          <step>D</step>
          <octave>5</octave>
        </pitch>
        <duration>96</duration>
        <type>quarter</type>
        <lyric>
          <syllabic>begin</syllabic>
          <text>cis</text>
        </lyric>
      </note>
    </measure>
    <measure number="10-0">
      <attributes />
      <note>
        
        <pitch>
          <step>A</step>
          <octave>4</octave>
        </pitch>
        <duration>96</duration>
        <type>quarter</type>
        <lyric>
          <syllabic>end</syllabic>
          <text>mi</text>
        </lyric>
      </note>
      <note>
        
        <pitch>
          <step>B</step>
          <alter>-0.5</alter>
          <octave>4</octave>
        </pitch>
        <duration>48</duration>
        <type>eighth</type>
        <accidental>quarter-flat</accidental>
        <lyric>
          <syllabic>single</syllabic>
          <text>mi </text>
        </lyric>
      </note>
      <note>
        
        <pitch>
          <step>C</step>
          <octave>5</octave>
        </pitch>
        <duration>72</duration>
        <type>eighth</type>
        <dot />
        <lyric>
          <syllabic>begin</syllabic>
          <text>per</text>
        </lyric>
      </note>
      <note>
        
        <pitch>
          <step>B</step>
          <alter>-0.5</alter>
          <octave>4</octave>
        </pitch>
        <duration>24</duration>
        <type>16th</type>
        <accidental>quarter-flat</accidental>
        <lyric>
          <text />
        </lyric>
      </note>
      <note>
        
        <pitch>
          <step>D</step>
          <octave>5</octave>
        </pitch>
        <duration>48</duration>
        <type>eighth</type>
        <lyric>
          <text />
        </lyric>
      </note>
      <note>
        
        <pitch>
          <step>C</step>
          <octave>5</octave>
        </pitch>
        <duration>24</duration>
        <type>16th</type>
        <lyric>
          <text />
        </lyric>
      </note>
      <note>
        
        <pitch>
          <step>B</step>
          <alter>-0.5</alter>
          <octave>4</octave>
        </pitch>
        <duration>24</duration>
        <type>16th</type>
        <accidental>quarter-flat</accidental>
        <lyric>
          <text />
        </lyric>
      </note>
      <note>
        
        <grace steal-time-previous="10" />
        <pitch>
          <step>C</step>
          <octave>5</octave>
        </pitch>
        <lyric>
          <text />
        </lyric>
      </note>
      <note>
        
        <pitch>
          <step>B</step>
          <alter>-0.5</alter>
          <octave>4</octave>
        </pitch>
        <duration>48</duration>
        <type>eighth</type>
        <accidental>quarter-flat</accidental>
        <lyric>
          <syllabic>end</syllabic>
          <text>v&#226; </text>
        </lyric>
      </note>
      <note>
        
        <pitch>
          <step>C</step>
          <octave>5</octave>
        </pitch>
        <duration>48</duration>
        <type>eighth</type>
        <lyric>
          <text />
        </lyric>
      </note>
      <note>
        
        <pitch>
          <step>B</step>
          <alter>-0.5</alter>
          <octave>4</octave>
        </pitch>
        <duration>24</duration>
        <type>16th</type>
        <accidental>quarter-flat</accidental>
        <lyric>
          <text />
        </lyric>
      </note>
      <note>
        
        <pitch>
          <step>A</step>
          <octave>4</octave>
        </pitch>
        <duration>24</duration>
        <type>16th</type>
        <lyric>
          <text />
        </lyric>
      </note>
      <note>
        
        <pitch>
          <step>A</step>
          <octave>4</octave>
        </pitch>
        <duration>144</duration>
        <type>quarter</type>
        <dot />
        <lyric>
          <text />
        </lyric>
      </note>
      <note>
        
        <rest />
        <duration>48</duration>
        <type>eighth</type>
        <lyric>
          <text />
        </lyric>
      </note>
    </measure>
    <measure number="11-0">
      <attributes />
      <note>
        
        <pitch>
          <step>G</step>
          <octave>5</octave>
        </pitch>
        <duration>96</duration>
        <type>quarter</type>
        <lyric>
          <syllabic>begin</syllabic>
          <text>v&#226;</text>
        </lyric>
      </note>
      <note>
        
        <pitch>
          <step>F</step>
          <alter>+1</alter>
          <octave>5</octave>
        </pitch>
        <duration>48</duration>
        <type>eighth</type>
        <accidental>sharp</accidental>
        <lyric>
          <text />
        </lyric>
      </note>
      <note>
        
        <pitch>
          <step>G</step>
          <octave>5</octave>
        </pitch>
        <duration>48</duration>
        <type>eighth</type>
        <lyric>
          <text />
        </lyric>
      </note>
      <note>
        
        <pitch>
          <step>F</step>
          <alter>+1</alter>
          <octave>5</octave>
        </pitch>
        <duration>48</duration>
        <type>eighth</type>
        <accidental>sharp</accidental>
        <lyric>
          <text />
        </lyric>
      </note>
      <note>
        
        <pitch>
          <step>E</step>
          <alter>-0.5</alter>
          <octave>5</octave>
        </pitch>
        <duration>48</duration>
        <type>eighth</type>
        <accidental>quarter-flat</accidental>
        <lyric>
          <text />
        </lyric>
      </note>
      <note>
        
        <pitch>
          <step>D</step>
          <octave>5</octave>
        </pitch>
        <duration>48</duration>
        <type>eighth</type>
        <lyric>
          <text />
        </lyric>
      </note>
      <note>
        
        <pitch>
          <step>D</step>
          <octave>5</octave>
        </pitch>
        <duration>96</duration>
        <type>quarter</type>
        <lyric>
          <text />
        </lyric>
      </note>
      <note>
        
        <pitch>
          <step>E</step>
          <alter>-0.5</alter>
          <octave>5</octave>
        </pitch>
        <duration>48</duration>
        <type>eighth</type>
        <accidental>quarter-flat</accidental>
        <lyric>
          <text />
        </lyric>
      </note>
      <note>
        
        <pitch>
          <step>F</step>
          <alter>+1</alter>
          <octave>5</octave>
        </pitch>
        <duration>48</duration>
        <type>eighth</type>
        <accidental>sharp</accidental>
        <lyric>
          <text />
        </lyric>
      </note>
      <note>
        
        <pitch>
          <step>G</step>
          <octave>5</octave>
        </pitch>
        <duration>48</duration>
        <type>eighth</type>
        <lyric>
          <text />
        </lyric>
      </note>
      <note>
        
        <pitch>
          <step>F</step>
          <alter>+1</alter>
          <octave>5</octave>
        </pitch>
        <duration>48</duration>
        <type>eighth</type>
        <accidental>sharp</accidental>
        <lyric>
          <text />
        </lyric>
      </note>
      <note>
        
        <pitch>
          <step>E</step>
          <alter>-0.5</alter>
          <octave>5</octave>
        </pitch>
        <duration>48</duration>
        <type>eighth</type>
        <accidental>quarter-flat</accidental>
        <lyric>
          <text />
        </lyric>
      </note>
    </measure>
    <measure number="12-0">
      <attributes />
      <note>
        
        <pitch>
          <step>D</step>
          <octave>5</octave>
        </pitch>
        <duration>96</duration>
        <type>quarter</type>
        <lyric>
          <syllabic>end</syllabic>
          <text>ne </text>
        </lyric>
      </note>
      <note>
        
        <pitch>
          <step>C</step>
          <octave>5</octave>
        </pitch>
        <duration>24</duration>
        <type>16th</type>
        <lyric>
          <syllabic>begin</syllabic>
          <text>d&#252;</text>
        </lyric>
      </note>
      <note>
        
        <pitch>
          <step>B</step>
          <alter>-0.5</alter>
          <octave>4</octave>
        </pitch>
        <duration>24</duration>
        <type>16th</type>
        <accidental>quarter-flat</accidental>
        <lyric>
          <text />
        </lyric>
      </note>
      <note>
        
        <pitch>
          <step>C</step>
          <octave>5</octave>
        </pitch>
        <duration>72</duration>
        <type>eighth</type>
        <dot />
        <lyric>
          <syllabic>end</syllabic>
          <text>&#351;&#252;r</text>
        </lyric>
      </note>
      <note>
        
        <pitch>
          <step>B</step>
          <alter>-0.5</alter>
          <octave>4</octave>
        </pitch>
        <duration>24</duration>
        <type>16th</type>
        <accidental>quarter-flat</accidental>
        <lyric>
          <text />
        </lyric>
      </note>
      <note>
        
        <pitch>
          <step>D</step>
          <octave>5</octave>
        </pitch>
        <duration>48</duration>
        <type>eighth</type>
        <lyric>
          <text />
        </lyric>
      </note>
      <note>
        
        <pitch>
          <step>C</step>
          <octave>5</octave>
        </pitch>
        <duration>24</duration>
        <type>16th</type>
        <lyric>
          <text />
        </lyric>
      </note>
      <note>
        
        <pitch>
          <step>B</step>
          <alter>-0.5</alter>
          <octave>4</octave>
        </pitch>
        <duration>24</duration>
        <type>16th</type>
        <accidental>quarter-flat</accidental>
        <lyric>
          <text />
        </lyric>
      </note>
      <note>
        
        <grace steal-time-previous="10" />
        <pitch>
          <step>C</step>
          <octave>5</octave>
        </pitch>
        <lyric>
          <text />
        </lyric>
      </note>
      <note>
        
        <pitch>
          <step>B</step>
          <alter>-0.5</alter>
          <octave>4</octave>
        </pitch>
        <duration>144</duration>
        <type>quarter</type>
        <dot />
        <accidental>quarter-flat</accidental>
        <lyric>
          <syllabic>single</syllabic>
          <text>d&#252;m  </text>
          <end-line />
        </lyric>
      </note>
      <note>
        
        <pitch>
          <step>B</step>
          <alter>-0.5</alter>
          <octave>4</octave>
        </pitch>
        <duration>48</duration>
        <type>eighth</type>
        <accidental>quarter-flat</accidental>
        <lyric>
          <text />
        </lyric>
      </note>
      <note>
        
        <pitch>
          <step>C</step>
          <octave>5</octave>
        </pitch>
        <duration>48</duration>
        <type>eighth</type>
        <lyric>
          <text />
        </lyric>
      </note>
      <note>
        
        <pitch>
          <step>D</step>
          <octave>5</octave>
        </pitch>
        <duration>96</duration>
        <type>quarter</type>
        <lyric>
          <text />
        </lyric>
      </note>
    </measure>
    <measure number="13-0">
      <attributes />
      <note>
        
        <pitch>
          <step>D</step>
          <octave>5</octave>
        </pitch>
        <duration>96</duration>
        <type>quarter</type>
        <lyric name="VOCAL_SECTION">
          <syllabic>begin</syllabic>
          <text>Ev</text>
        </lyric>
      </note>
      <note>
        
        <pitch>
          <step>E</step>
          <octave>5</octave>
        </pitch>
        <duration>48</duration>
        <type>eighth</type>
        <lyric>
          <text />
        </lyric>
      </note>
      <note>
        
        <pitch>
          <step>D</step>
          <octave>5</octave>
        </pitch>
        <duration>48</duration>
        <type>eighth</type>
        <lyric>
          <syllabic>end</syllabic>
          <text>r&#226;k_</text>
        </lyric>
      </note>
      <note>
        
        <pitch>
          <step>C</step>
          <octave>5</octave>
        </pitch>
        <duration>24</duration>
        <type>16th</type>
        <lyric>
          <text />
        </lyric>
      </note>
      <note>
        
        <pitch>
          <step>D</step>
          <octave>5</octave>
        </pitch>
        <duration>24</duration>
        <type>16th</type>
        <lyric>
          <text />
        </lyric>
      </note>
      <note>
        
        <pitch>
          <step>C</step>
          <octave>5</octave>
        </pitch>
        <duration>48</duration>
        <type>eighth</type>
        <lyric>
          <text />
        </lyric>
      </note>
      <note>
        
        <pitch>
          <step>B</step>
          <alter>-0.5</alter>
          <octave>4</octave>
        </pitch>
        <duration>48</duration>
        <type>eighth</type>
        <accidental>quarter-flat</accidental>
        <lyric>
          <text />
        </lyric>
      </note>
      <note>
        
        <pitch>
          <step>A</step>
          <octave>4</octave>
        </pitch>
        <duration>48</duration>
        <type>eighth</type>
        <lyric>
          <syllabic>single</syllabic>
          <text>&#305; </text>
        </lyric>
      </note>
      <note>
        
        <grace steal-time-previous="10" />
        <pitch>
          <step>B</step>
          <octave>4</octave>
        </pitch>
        <lyric>
          <text />
        </lyric>
      </note>
      <note>
        
        <pitch>
          <step>A</step>
          <octave>4</octave>
        </pitch>
        <duration>48</duration>
        <type>eighth</type>
        <lyric>
          <text />
        </lyric>
      </note>
      <note>
        
        <pitch>
          <step>B</step>
          <alter>-0.5</alter>
          <octave>4</octave>
        </pitch>
        <duration>48</duration>
        <type>eighth</type>
        <accidental>quarter-flat</accidental>
        <lyric>
          <syllabic>begin</syllabic>
          <text>di</text>
        </lyric>
      </note>
      <note>
        
        <pitch>
          <step>C</step>
          <octave>5</octave>
        </pitch>
        <duration>48</duration>
        <type>eighth</type>
        <lyric>
          <syllabic>end</syllabic>
          <text>li </text>
        </lyric>
      </note>
      <note>
        
        <pitch>
          <step>B</step>
          <alter>-0.5</alter>
          <octave>4</octave>
        </pitch>
        <duration>24</duration>
        <type>16th</type>
        <accidental>quarter-flat</accidental>
        <lyric>
          <text />
        </lyric>
      </note>
      <note>
        
        <pitch>
          <step>C</step>
          <octave>5</octave>
        </pitch>
        <duration>24</duration>
        <type>16th</type>
        <lyric>
          <text />
        </lyric>
      </note>
      <note>
        
        <pitch>
          <step>D</step>
          <octave>5</octave>
        </pitch>
        <duration>96</duration>
        <type>quarter</type>
        <lyric>
          <syllabic>begin</syllabic>
          <text>&#226;</text>
        </lyric>
      </note>
    </measure>
    <measure number="14-0">
      <attributes />
      <note>
        
        <pitch>
          <step>A</step>
          <octave>4</octave>
        </pitch>
        <duration>96</duration>
        <type>quarter</type>
        <lyric>
          <syllabic>end</syllabic>
          <text>te&#351;_</text>
        </lyric>
      </note>
      <note>
        
        <pitch>
          <step>B</step>
          <alter>-0.5</alter>
          <octave>4</octave>
        </pitch>
        <duration>48</duration>
        <type>eighth</type>
        <accidental>quarter-flat</accidental>
        <lyric>
          <syllabic>single</syllabic>
          <text>i </text>
        </lyric>
      </note>
      <note>
        
        <pitch>
          <step>C</step>
          <octave>5</octave>
        </pitch>
        <duration>72</duration>
        <type>eighth</type>
        <dot />
        <lyric>
          <syllabic>begin</syllabic>
          <text>s&#251;</text>
        </lyric>
      </note>
      <note>
        
        <pitch>
          <step>B</step>
          <alter>-0.5</alter>
          <octave>4</octave>
        </pitch>
        <duration>24</duration>
        <type>16th</type>
        <accidental>quarter-flat</accidental>
        <lyric>
          <text />
        </lyric>
      </note>
      <note>
        
        <pitch>
          <step>D</step>
          <octave>5</octave>
        </pitch>
        <duration>48</duration>
        <type>eighth</type>
        <lyric>
          <text />
        </lyric>
      </note>
      <note>
        
        <pitch>
          <step>C</step>
          <octave>5</octave>
        </pitch>
        <duration>24</duration>
        <type>16th</type>
        <lyric>
          <text />
        </lyric>
      </note>
      <note>
        
        <pitch>
          <step>B</step>
          <alter>-0.5</alter>
          <octave>4</octave>
        </pitch>
        <duration>24</duration>
        <type>16th</type>
        <accidental>quarter-flat</accidental>
        <lyric>
          <text />
        </lyric>
      </note>
      <note>
        
        <grace steal-time-previous="10" />
        <pitch>
          <step>C</step>
          <octave>5</octave>
        </pitch>
        <lyric>
          <text />
        </lyric>
      </note>
      <note>
        
        <pitch>
          <step>B</step>
          <alter>-0.5</alter>
          <octave>4</octave>
        </pitch>
        <duration>48</duration>
        <type>eighth</type>
        <accidental>quarter-flat</accidental>
        <lyric>
          <syllabic>end</syllabic>
          <text>z&#226; </text>
        </lyric>
      </note>
      <note>
        
        <pitch>
          <step>C</step>
          <octave>5</octave>
        </pitch>
        <duration>48</duration>
        <type>eighth</type>
        <lyric>
          <text />
        </lyric>
      </note>
      <note>
        
        <pitch>
          <step>B</step>
          <alter>-0.5</alter>
          <octave>4</octave>
        </pitch>
        <duration>24</duration>
        <type>16th</type>
        <accidental>quarter-flat</accidental>
        <lyric>
          <text />
        </lyric>
      </note>
      <note>
        
        <pitch>
          <step>A</step>
          <octave>4</octave>
        </pitch>
        <duration>24</duration>
        <type>16th</type>
        <lyric>
          <text />
        </lyric>
      </note>
      <note>
        
        <pitch>
          <step>A</step>
          <octave>4</octave>
        </pitch>
        <duration>144</duration>
        <type>quarter</type>
        <dot />
        <lyric>
          <text />
        </lyric>
      </note>
      <note>
        
        <rest />
        <duration>48</duration>
        <type>eighth</type>
        <lyric>
          <text />
        </lyric>
      </note>
    </measure>
    <measure number="15-0">
      <attributes />
      <note>
        
        <pitch>
          <step>G</step>
          <octave>5</octave>
        </pitch>
        <duration>96</duration>
        <type>quarter</type>
        <lyric>
          <syllabic>begin</syllabic>
          <text>z&#226;</text>
        </lyric>
      </note>
      <note>
        
        <pitch>
          <step>F</step>
          <alter>+1</alter>
          <octave>5</octave>
        </pitch>
        <duration>48</duration>
        <type>eighth</type>
        <accidental>sharp</accidental>
        <lyric>
          <text />
        </lyric>
      </note>
      <note>
        
        <pitch>
          <step>G</step>
          <octave>5</octave>
        </pitch>
        <duration>48</duration>
        <type>eighth</type>
        <lyric>
          <text />
        </lyric>
      </note>
      <note>
        
        <pitch>
          <step>F</step>
          <alter>+1</alter>
          <octave>5</octave>
        </pitch>
        <duration>48</duration>
        <type>eighth</type>
        <accidental>sharp</accidental>
        <lyric>
          <text />
        </lyric>
      </note>
      <note>
        
        <pitch>
          <step>E</step>
          <alter>-0.5</alter>
          <octave>5</octave>
        </pitch>
        <duration>48</duration>
        <type>eighth</type>
        <accidental>quarter-flat</accidental>
        <lyric>
          <text />
        </lyric>
      </note>
      <note>
        
        <pitch>
          <step>D</step>
          <octave>5</octave>
        </pitch>
        <duration>48</duration>
        <type>eighth</type>
        <lyric>
          <text />
        </lyric>
      </note>
      <note>
        
        <pitch>
          <step>D</step>
          <octave>5</octave>
        </pitch>
        <duration>96</duration>
        <type>quarter</type>
        <lyric>
          <text />
        </lyric>
      </note>
      <note>
        
        <pitch>
          <step>E</step>
          <alter>-0.5</alter>
          <octave>5</octave>
        </pitch>
        <duration>48</duration>
        <type>eighth</type>
        <accidental>quarter-flat</accidental>
        <lyric>
          <text />
        </lyric>
      </note>
      <note>
        
        <pitch>
          <step>F</step>
          <alter>+1</alter>
          <octave>5</octave>
        </pitch>
        <duration>48</duration>
        <type>eighth</type>
        <accidental>sharp</accidental>
        <lyric>
          <text />
        </lyric>
      </note>
      <note>
        
        <pitch>
          <step>G</step>
          <octave>5</octave>
        </pitch>
        <duration>48</duration>
        <type>eighth</type>
        <lyric>
          <text />
        </lyric>
      </note>
      <note>
        
        <pitch>
          <step>F</step>
          <alter>+1</alter>
          <octave>5</octave>
        </pitch>
        <duration>48</duration>
        <type>eighth</type>
        <accidental>sharp</accidental>
        <lyric>
          <text />
        </lyric>
      </note>
      <note>
        
        <pitch>
          <step>E</step>
          <alter>-0.5</alter>
          <octave>5</octave>
        </pitch>
        <duration>48</duration>
        <type>eighth</type>
        <accidental>quarter-flat</accidental>
        <lyric>
          <text />
        </lyric>
      </note>
    </measure>
    <measure number="16-0">
      <attributes />
      <note>
        
        <pitch>
          <step>D</step>
          <octave>5</octave>
        </pitch>
        <duration>96</duration>
        <type>quarter</type>
        <lyric>
          <syllabic>end</syllabic>
          <text>ne </text>
        </lyric>
      </note>
      <note>
        
        <pitch>
          <step>C</step>
          <octave>5</octave>
        </pitch>
        <duration>24</duration>
        <type>16th</type>
        <lyric>
          <syllabic>begin</syllabic>
          <text>d&#252;</text>
        </lyric>
      </note>
      <note>
        
        <pitch>
          <step>B</step>
          <alter>-0.5</alter>
          <octave>4</octave>
        </pitch>
        <duration>24</duration>
        <type>16th</type>
        <accidental>quarter-flat</accidental>
        <lyric>
          <text />
        </lyric>
      </note>
      <note>
        
        <pitch>
          <step>C</step>
          <octave>5</octave>
        </pitch>
        <duration>72</duration>
        <type>eighth</type>
        <dot />
        <lyric>
          <syllabic>end</syllabic>
          <text>&#351;&#252;r</text>
        </lyric>
      </note>
      <note>
        
        <pitch>
          <step>B</step>
          <alter>-0.5</alter>
          <octave>4</octave>
        </pitch>
        <duration>24</duration>
        <type>16th</type>
        <accidental>quarter-flat</accidental>
        <lyric>
          <text />
        </lyric>
      </note>
      <note>
        
        <pitch>
          <step>D</step>
          <octave>5</octave>
        </pitch>
        <duration>48</duration>
        <type>eighth</type>
        <lyric>
          <text />
        </lyric>
      </note>
      <note>
        
        <pitch>
          <step>C</step>
          <octave>5</octave>
        </pitch>
        <duration>24</duration>
        <type>16th</type>
        <lyric>
          <text />
        </lyric>
      </note>
      <note>
        
        <pitch>
          <step>B</step>
          <alter>-0.5</alter>
          <octave>4</octave>
        </pitch>
        <duration>24</duration>
        <type>16th</type>
        <accidental>quarter-flat</accidental>
        <lyric>
          <text />
        </lyric>
      </note>
      <note>
        
        <grace steal-time-previous="10" />
        <pitch>
          <step>C</step>
          <octave>5</octave>
        </pitch>
        <lyric>
          <text />
        </lyric>
      </note>
      <note>
        
        <pitch>
          <step>B</step>
          <alter>-0.5</alter>
          <octave>4</octave>
        </pitch>
        <duration>144</duration>
        <type>quarter</type>
        <dot />
        <accidental>quarter-flat</accidental>
        <lyric>
          <syllabic>single</syllabic>
          <text>d&#252;m  </text>
          <end-line />
        </lyric>
      </note>
      <note>
        
        <pitch>
          <step>B</step>
          <alter>-0.5</alter>
          <octave>4</octave>
        </pitch>
        <duration>48</duration>
        <type>eighth</type>
        <accidental>quarter-flat</accidental>
        <lyric>
          <text />
        </lyric>
      </note>
      <note>
        
        <pitch>
          <step>C</step>
          <octave>5</octave>
        </pitch>
        <duration>48</duration>
        <type>eighth</type>
        <lyric>
          <text />
        </lyric>
      </note>
      <note>
        
        <pitch>
          <step>D</step>
          <octave>5</octave>
        </pitch>
        <duration>96</duration>
        <type>quarter</type>
        <lyric>
          <text />
        </lyric>
      </note>
    </measure>
    <measure number="17-0">
      <attributes />
      <note>
        
        <pitch>
          <step>D</step>
          <octave>5</octave>
        </pitch>
        <duration>96</duration>
        <type>quarter</type>
        <lyric name="VOCAL_SECTION">
          <syllabic>begin</syllabic>
          <text>Mev</text>
        </lyric>
      </note>
      <note>
        
        <pitch>
          <step>E</step>
          <octave>5</octave>
        </pitch>
        <duration>48</duration>
        <type>eighth</type>
        <lyric>
          <text />
        </lyric>
      </note>
      <note>
        
        <pitch>
          <step>D</step>
          <octave>5</octave>
        </pitch>
        <duration>48</duration>
        <type>eighth</type>
        <lyric>
          <syllabic>end</syllabic>
          <text>l&#226;</text>
        </lyric>
      </note>
      <note>
        
        <pitch>
          <step>C</step>
          <octave>5</octave>
        </pitch>
        <duration>24</duration>
        <type>16th</type>
        <lyric>
          <text />
        </lyric>
      </note>
      <note>
        
        <pitch>
          <step>D</step>
          <octave>5</octave>
        </pitch>
        <duration>24</duration>
        <type>16th</type>
        <lyric>
          <text />
        </lyric>
      </note>
      <note>
        
        <pitch>
          <step>C</step>
          <octave>5</octave>
        </pitch>
        <duration>48</duration>
        <type>eighth</type>
        <lyric>
          <text />
        </lyric>
      </note>
      <note>
        
        <pitch>
          <step>B</step>
          <alter>-0.5</alter>
          <octave>4</octave>
        </pitch>
        <duration>48</duration>
        <type>eighth</type>
        <accidental>quarter-flat</accidental>
        <lyric>
          <text />
        </lyric>
      </note>
      <note>
        
        <pitch>
          <step>A</step>
          <octave>4</octave>
        </pitch>
        <duration>48</duration>
        <type>eighth</type>
        <lyric>
          <syllabic>single</syllabic>
          <text>y&#305; </text>
        </lyric>
      </note>
      <note>
        
        <grace steal-time-previous="10" />
        <pitch>
          <step>B</step>
          <octave>4</octave>
        </pitch>
        <lyric>
          <text />
        </lyric>
      </note>
      <note>
        
        <pitch>
          <step>A</step>
          <octave>4</octave>
        </pitch>
        <duration>48</duration>
        <type>eighth</type>
        <lyric>
          <text />
        </lyric>
      </note>
      <note>
        
        <pitch>
          <step>B</step>
          <alter>-0.5</alter>
          <octave>4</octave>
        </pitch>
        <duration>48</duration>
        <type>eighth</type>
        <accidental>quarter-flat</accidental>
        <lyric>
          <syllabic>begin</syllabic>
          <text>se</text>
        </lyric>
      </note>
      <note>
        
        <pitch>
          <step>C</step>
          <octave>5</octave>
        </pitch>
        <duration>48</duration>
        <type>eighth</type>
        <lyric>
          <syllabic>end</syllabic>
          <text>ver</text>
        </lyric>
      </note>
      <note>
        
        <pitch>
          <step>B</step>
          <alter>-0.5</alter>
          <octave>4</octave>
        </pitch>
        <duration>24</duration>
        <type>16th</type>
        <accidental>quarter-flat</accidental>
        <lyric>
          <text />
        </lyric>
      </note>
      <note>
        
        <pitch>
          <step>C</step>
          <octave>5</octave>
        </pitch>
        <duration>24</duration>
        <type>16th</type>
        <lyric>
          <text />
        </lyric>
      </note>
      <note>
        
        <pitch>
          <step>D</step>
          <octave>5</octave>
        </pitch>
        <duration>96</duration>
        <type>quarter</type>
        <lyric>
          <syllabic>single</syllabic>
          <text>sen </text>
        </lyric>
      </note>
    </measure>
    <measure number="18-0">
      <attributes />
      <note>
        
        <pitch>
          <step>A</step>
          <octave>4</octave>
        </pitch>
        <duration>96</duration>
        <type>quarter</type>
        <lyric>
          <syllabic>begin</syllabic>
          <text>be</text>
        </lyric>
      </note>
      <note>
        
        <pitch>
          <step>B</step>
          <alter>-0.5</alter>
          <octave>4</octave>
        </pitch>
        <duration>48</duration>
        <type>eighth</type>
        <accidental>quarter-flat</accidental>
        <lyric>
          <syllabic>end</syllabic>
          <text>ni </text>
        </lyric>
      </note>
      <note>
        
        <pitch>
          <step>C</step>
          <octave>5</octave>
        </pitch>
        <duration>72</duration>
        <type>eighth</type>
        <dot />
        <lyric>
          <syllabic>begin</syllabic>
          <text>s&#246;y</text>
        </lyric>
      </note>
      <note>
        
        <pitch>
          <step>B</step>
          <alter>-0.5</alter>
          <octave>4</octave>
        </pitch>
        <duration>24</duration>
        <type>16th</type>
        <accidental>quarter-flat</accidental>
        <lyric>
          <text />
        </lyric>
      </note>
      <note>
        
        <pitch>
          <step>D</step>
          <octave>5</octave>
        </pitch>
        <duration>48</duration>
        <type>eighth</type>
        <lyric>
          <text />
        </lyric>
      </note>
      <note>
        
        <pitch>
          <step>C</step>
          <octave>5</octave>
        </pitch>
        <duration>24</duration>
        <type>16th</type>
        <lyric>
          <text />
        </lyric>
      </note>
      <note>
        
        <pitch>
          <step>B</step>
          <alter>-0.5</alter>
          <octave>4</octave>
        </pitch>
        <duration>24</duration>
        <type>16th</type>
        <accidental>quarter-flat</accidental>
        <lyric>
          <text />
        </lyric>
      </note>
      <note>
        
        <grace steal-time-previous="10" />
        <pitch>
          <step>C</step>
          <octave>5</octave>
        </pitch>
        <lyric>
          <text />
        </lyric>
      </note>
      <note>
        
        <pitch>
          <step>B</step>
          <alter>-0.5</alter>
          <octave>4</octave>
        </pitch>
        <duration>48</duration>
        <type>eighth</type>
        <accidental>quarter-flat</accidental>
        <lyric>
          <syllabic>end</syllabic>
          <text>let </text>
        </lyric>
      </note>
      <note>
        
        <pitch>
          <step>C</step>
          <octave>5</octave>
        </pitch>
        <duration>48</duration>
        <type>eighth</type>
        <lyric>
          <text />
        </lyric>
      </note>
      <note>
        
        <pitch>
          <step>B</step>
          <alter>-0.5</alter>
          <octave>4</octave>
        </pitch>
        <duration>24</duration>
        <type>16th</type>
        <accidental>quarter-flat</accidental>
        <lyric>
          <text />
        </lyric>
      </note>
      <note>
        
        <pitch>
          <step>A</step>
          <octave>4</octave>
        </pitch>
        <duration>24</duration>
        <type>16th</type>
        <lyric>
          <text />
        </lyric>
      </note>
      <note>
        
        <pitch>
          <step>A</step>
          <octave>4</octave>
        </pitch>
        <duration>144</duration>
        <type>quarter</type>
        <dot />
        <lyric>
          <text />
        </lyric>
      </note>
      <note>
        
        <rest />
        <duration>48</duration>
        <type>eighth</type>
        <lyric>
          <text />
        </lyric>
      </note>
    </measure>
    <measure number="19-0">
      <attributes />
      <note>
        
        <pitch>
          <step>G</step>
          <octave>5</octave>
        </pitch>
        <duration>96</duration>
        <type>quarter</type>
        <lyric>
          <syllabic>begin</syllabic>
          <text>let</text>
        </lyric>
      </note>
      <note>
        
        <pitch>
          <step>F</step>
          <alter>+1</alter>
          <octave>5</octave>
        </pitch>
        <duration>48</duration>
        <type>eighth</type>
        <accidental>sharp</accidental>
        <lyric>
          <text />
        </lyric>
      </note>
      <note>
        
        <pitch>
          <step>G</step>
          <octave>5</octave>
        </pitch>
        <duration>48</duration>
        <type>eighth</type>
        <lyric>
          <text />
        </lyric>
      </note>
      <note>
        
        <pitch>
          <step>F</step>
          <alter>+1</alter>
          <octave>5</octave>
        </pitch>
        <duration>48</duration>
        <type>eighth</type>
        <accidental>sharp</accidental>
        <lyric>
          <text />
        </lyric>
      </note>
      <note>
        
        <pitch>
          <step>E</step>
          <alter>-0.5</alter>
          <octave>5</octave>
        </pitch>
        <duration>48</duration>
        <type>eighth</type>
        <accidental>quarter-flat</accidental>
        <lyric>
          <text />
        </lyric>
      </note>
      <note>
        
        <pitch>
          <step>D</step>
          <octave>5</octave>
        </pitch>
        <duration>48</duration>
        <type>eighth</type>
        <lyric>
          <text />
        </lyric>
      </note>
      <note>
        
        <pitch>
          <step>D</step>
          <octave>5</octave>
        </pitch>
        <duration>96</duration>
        <type>quarter</type>
        <lyric>
          <text />
        </lyric>
      </note>
      <note>
        
        <pitch>
          <step>E</step>
          <alter>-0.5</alter>
          <octave>5</octave>
        </pitch>
        <duration>48</duration>
        <type>eighth</type>
        <accidental>quarter-flat</accidental>
        <lyric>
          <text />
        </lyric>
      </note>
      <note>
        
        <pitch>
          <step>F</step>
          <alter>+1</alter>
          <octave>5</octave>
        </pitch>
        <duration>48</duration>
        <type>eighth</type>
        <accidental>sharp</accidental>
        <lyric>
          <text />
        </lyric>
      </note>
      <note>
        
        <pitch>
          <step>G</step>
          <octave>5</octave>
        </pitch>
        <duration>48</duration>
        <type>eighth</type>
        <lyric>
          <text />
        </lyric>
      </note>
      <note>
        
        <pitch>
          <step>F</step>
          <alter>+1</alter>
          <octave>5</octave>
        </pitch>
        <duration>48</duration>
        <type>eighth</type>
        <accidental>sharp</accidental>
        <lyric>
          <text />
        </lyric>
      </note>
      <note>
        
        <pitch>
          <step>E</step>
          <alter>-0.5</alter>
          <octave>5</octave>
        </pitch>
        <duration>48</duration>
        <type>eighth</type>
        <accidental>quarter-flat</accidental>
        <lyric>
          <text />
        </lyric>
      </note>
    </measure>
    <measure number="20-0">
      <attributes />
      <note>
        
        <pitch>
          <step>D</step>
          <octave>5</octave>
        </pitch>
        <duration>96</duration>
        <type>quarter</type>
        <lyric>
          <syllabic>end</syllabic>
          <text>me </text>
        </lyric>
      </note>
      <note>
        
        <pitch>
          <step>C</step>
          <octave>5</octave>
        </pitch>
        <duration>24</duration>
        <type>16th</type>
        <lyric>
          <syllabic>begin</syllabic>
          <text>ga</text>
        </lyric>
      </note>
      <note>
        
        <pitch>
          <step>B</step>
          <alter>-0.5</alter>
          <octave>4</octave>
        </pitch>
        <duration>24</duration>
        <type>16th</type>
        <accidental>quarter-flat</accidental>
        <lyric>
          <text />
        </lyric>
      </note>
      <note>
        
        <pitch>
          <step>C</step>
          <octave>5</octave>
        </pitch>
        <duration>72</duration>
        <type>eighth</type>
        <dot />
        <lyric>
          <syllabic>end</syllabic>
          <text>m&#305;m </text>
        </lyric>
      </note>
      <note>
        
        <pitch>
          <step>B</step>
          <alter>-0.5</alter>
          <octave>4</octave>
        </pitch>
        <duration>24</duration>
        <type>16th</type>
        <accidental>quarter-flat</accidental>
        <lyric>
          <text />
        </lyric>
      </note>
      <note>
        
        <pitch>
          <step>D</step>
          <octave>5</octave>
        </pitch>
        <duration>48</duration>
        <type>eighth</type>
        <lyric>
          <text />
        </lyric>
      </note>
      <note>
        
        <pitch>
          <step>C</step>
          <octave>5</octave>
        </pitch>
        <duration>24</duration>
        <type>16th</type>
        <lyric>
          <text />
        </lyric>
      </note>
      <note>
        
        <pitch>
          <step>B</step>
          <alter>-0.5</alter>
          <octave>4</octave>
        </pitch>
        <duration>24</duration>
        <type>16th</type>
        <accidental>quarter-flat</accidental>
        <lyric>
          <text />
        </lyric>
      </note>
      <note>
        
        <grace steal-time-previous="10" />
        <pitch>
          <step>C</step>
          <octave>5</octave>
        </pitch>
        <lyric>
          <text />
        </lyric>
      </note>
      <note>
        
        <pitch>
          <step>B</step>
          <alter>-0.5</alter>
          <octave>4</octave>
        </pitch>
        <duration>96</duration>
        <type>quarter</type>
        <accidental>quarter-flat</accidental>
        <lyric>
          <syllabic>single</syllabic>
          <text>var  </text>
          <end-line />
        </lyric>
      </note>
      <note>
        
        <pitch>
          <step>B</step>
          <alter>-0.5</alter>
          <octave>4</octave>
        </pitch>
        <duration>144</duration>
        <type>quarter</type>
        <dot />
        <accidental>quarter-flat</accidental>
        <lyric>
          <syllabic>begin</syllabic>
          <text>_</text>
        </lyric>
      </note>
      <note>
        
        <rest />
        <duration>96</duration>
        <type>quarter</type>
        <lyric>
          <text />
        </lyric>
      </note>
    </measure>
    <measure number="21-0">
      <attributes />
    </measure>
  </part>
</score-partwise>